{
  "Assets.NAME[RoadBuilder.LaneGroups.BusGroupPrefab]": "Otobüs",
  "Assets.NAME[RoadBuilder.LaneGroups.CarGroupPrefab]": "Araba",
  "Assets.NAME[RoadBuilder.LaneGroups.MedianGroupPrefab]": "Refüj",
  "Assets.NAME[RoadBuilder.LaneGroups.ShoulderGroupPrefab]": "Kenar",
  "Assets.NAME[RoadBuilder.LaneGroups.EmptyGroupPrefab]": "Boş Şerit",
  "Assets.NAME[RoadBuilder.LaneGroups.SidewalkGroupPrefab]": "Kaldırım",
  "Assets.NAME[RoadBuilder.LaneGroups.SubwayGroupPrefab]": "Metro Rayı",
  "Assets.NAME[RoadBuilder.LaneGroups.SubwayMedianGroupPrefab]": "Peron",
  "Assets.NAME[RoadBuilder.LaneGroups.TrainGroupPrefab]": "Tren Rayı",
  "Assets.NAME[RoadBuilder.LaneGroups.TramGroupPrefab]": "Tramvay Rayı",
  "Assets.NAME[RoadBuilder.LaneGroups.ParkingGroupPrefab]": "Park Etme",
  "Assets.NAME[RoadBuilder.LaneGroups.PoleGroupPrefab]": "Direk",
  "RoadBuilder.LaneGroups.BusGroupPrefab.Options[Lane Width]": "Şerit Genişliği",
  "RoadBuilder.LaneGroups.BusGroupPrefab.Options[Transport Option]": "Ulaşım Seçenekleri",
  "RoadBuilder.LaneGroups.CarGroupPrefab.Options[Lane Width]": "Şerit Genişliği",
  "RoadBuilder.LaneGroups.CarGroupPrefab.Options[Transport Option]": "Ulaşım Seçenekleri",
  "RoadBuilder.LaneGroups.CarGroupPrefab.Options[Markings]": "İşaretlemeler",
  "RoadBuilder.LaneGroups.MedianGroupPrefab.Options[Median Width]": "Refüj Genişliği",
  "RoadBuilder.LaneGroups.ShoulderGroupPrefab.Options[Lane Width]": "Şerit Genişliği",
  "RoadBuilder.LaneGroups.ShoulderGroupPrefab.Options[Ground Type]": "Zemin Türü",
  "RoadBuilder.LaneGroups.EmptyGroupPrefab.Options[Lane Width]": "Şerit Genişliği",
  "RoadBuilder.LaneGroups.EmptyGroupPrefab.Options[Ground Type]": "Zemin Türü",
  "RoadBuilder.LaneGroups.SidewalkGroupPrefab.Options[Transport]": "Ulaşım Seçenekleri",
  "RoadBuilder.LaneGroups.SidewalkGroupPrefab.Options[Width]": "Şerit Genişliği",
  "RoadBuilder.LaneGroups.SidewalkGroupPrefab.Options[Parking]": "Park Etme",
  "RoadBuilder.LaneGroups.SubwayMedianGroupPrefab.Options[Style]": "Yükseklik",
  "RoadBuilder.LaneGroups.ParkingGroupPrefab.Options[Parking Angle]": "Park Etme Açısı",
  "RoadBuilder.LaneGroups.ParkingGroupPrefab.Options[Markings]": "İşaretlemeler",
  "RoadBuilder.LaneGroups.PoleGroupPrefab.Options[Lane Width]": "Şerit Genişliği",
  "RoadBuilder.LaneGroups.PoleGroupPrefab.Options[Ground Type]": "Zemin Türü",
  "RoadBuilder.LaneGroups.BusGroupPrefab.Options[Transport Option][]": "Sadece Otobüs",
  "RoadBuilder.LaneGroups.BusGroupPrefab.Options[Transport Option][Tram]": "Otobüs ve Tramvay Ortak",
  "RoadBuilder.LaneGroups.CarGroupPrefab.Options[Transport Option][]": "Sadece Araba",
  "RoadBuilder.LaneGroups.CarGroupPrefab.Options[Transport Option][Transport]": "Araba ve Otobüs Ortak",
  "RoadBuilder.LaneGroups.CarGroupPrefab.Options[Transport Option][Tram]": "Araba ve Otobüs veya Tramvay Ortak",
  "RoadBuilder.LaneGroups.CarGroupPrefab.Options[Markings][]": "İşaretlemeli",
  "RoadBuilder.LaneGroups.CarGroupPrefab.Options[Markings][1]": "İşaretlemeleri Kaldır",
  "RoadBuilder.LaneGroups.SidewalkGroupPrefab.Options[Parking][]": "Yolkenarı park etmeye izin verme",
  "RoadBuilder.LaneGroups.SidewalkGroupPrefab.Options[Parking][P]": "Yolkenarı park etmeye izin ver",
  "RoadBuilder.LaneGroups.SubwayMedianGroupPrefab.Options[Style][Raised]": "Yüksek peron",
  "RoadBuilder.LaneGroups.SubwayMedianGroupPrefab.Options[Style][Flat]": "Alçak Peron",
  "RoadBuilder.LaneGroups.ParkingGroupPrefab.Options[Parking Angle][Parallel]": "Paralel",
  "RoadBuilder.LaneGroups.ParkingGroupPrefab.Options[Parking Angle][Angled]": "Açılı",
  "RoadBuilder.LaneGroups.ParkingGroupPrefab.Options[Parking Angle][Perpendicular]": "Dik",
  "RoadBuilder.LaneGroups.ParkingGroupPrefab.Options[Markings][1]": "İşaretlemeli",
  "RoadBuilder.LaneGroups.ParkingGroupPrefab.Options[Markings][]": "İşaretlemeleri Kaldır",
  "RoadBuilder.LaneGroups.ShoulderGroupPrefab.Options[Ground Type][Asphalt]": "Asfalt",
  "RoadBuilder.LaneGroups.ShoulderGroupPrefab.Options[Ground Type][Bus]": "Otobüs",
  "RoadBuilder.LaneGroups.ShoulderGroupPrefab.Options[Ground Type][Tram]": "Tramvay",
  "RoadBuilder.LaneGroups.ShoulderGroupPrefab.Options[Ground Type][Train]": "Tren",
  "RoadBuilder.LaneGroups.ShoulderGroupPrefab.Options[Ground Type][Subway]": "Metro",
  "RoadBuilder.LaneGroups.ShoulderGroupPrefab.Options[Ground Type][Gravel]": "Çakıl",
  "RoadBuilder.LaneGroups.ShoulderGroupPrefab.Options[Ground Type][Tiled]": "Döşeli",
  "RoadBuilder.LaneGroups.EmptyGroupPrefab.Options[Ground Type][Asphalt]": "Asfalt",
  "RoadBuilder.LaneGroups.EmptyGroupPrefab.Options[Ground Type][Train]": "Tren",
  "RoadBuilder.LaneGroups.EmptyGroupPrefab.Options[Ground Type][Gravel]": "Çakıl",
  "RoadBuilder.LaneGroups.EmptyGroupPrefab.Options[Ground Type][Tiled]": "Döşeli",
  "Assets.NAME[RB Sound Barrier 1]": "Sound Barrier",
  "Assets.NAME[Pavement Path Section 3]": "Yaya Kaldırımı",
  "Assets.NAME[Tiled Pedestrian Section 3]": "Döşenmiş Yaya Yolu",
  "Assets.NAME[RB Tiled Median 2]": "Döşenmiş Refüj"
}
